my_package/__init__.py
my_package/main.py
urvi2107_my_first_package-0.1.0.dist-info/METADATA
urvi2107_my_first_package-0.1.0.dist-info/WHEEL
urvi2107_my_first_package-0.1.0.dist-info/top_level.txt
urvi2107_my_first_package-0.1.0.dist-info/RECORD
