Metadata-Version: 2.4
Name: urvi2107_my_first_package
Version: 0.1.0
Summary: This is my first Python package
Author-email: Urvi Nath <nath.urvi@gmail.com>
License-Expression: MIT
